audiofoundry/__init__.py
audiofoundry-0.1.0.dist-info/COPYING
audiofoundry-0.1.0.dist-info/METADATA
audiofoundry-0.1.0.dist-info/WHEEL
audiofoundry-0.1.0.dist-info/RECORD
